{
	"info": {
		"_postman_id": "9c0718b3-be43-44e1-ad53-6bf81b2e1e00",
		"name": "Flask REST API",
		"schema": "https://schema.getpostman.com/json/collection/v2.1.0/collection.json"
	},
	"item": [
		{
			"name": "Login",
			"protocolProfileBehavior": {
				"disabledSystemHeaders": {
					"accept": true
				}
			},
			"request": {
				"auth": {
					"type": "noauth"
				},
				"method": "POST",
				"header": [
					{
						"key": "Accept",
						"value": "application/json",
						"type": "default"
					},
					{
						"key": "Content-Type",
						"value": "application/json",
						"type": "default"
					}
				],
				"body": {
					"mode": "raw",
					"raw": "{\r\n    \"login\": \"user\",\r\n    \"password\": \"password\"\r\n}"
				},
				"url": {
					"raw": "http://127.0.0.1:5000/api/login",
					"protocol": "http",
					"host": [
						"127",
						"0",
						"0",
						"1"
					],
					"port": "5000",
					"path": [
						"api",
						"login"
					]
				}
			},
			"response": []
		},
		{
			"name": "Register",
			"request": {
				"method": "POST",
				"header": [],
				"body": {
					"mode": "raw",
					"raw": "{\r\n    \"login\": \"user\",\r\n    \"password\": \"password\"\r\n}",
					"options": {
						"raw": {
							"language": "json"
						}
					}
				},
				"url": {
					"raw": "http://127.0.0.1:5000/api/registration",
					"protocol": "http",
					"host": [
						"127",
						"0",
						"0",
						"1"
					],
					"port": "5000",
					"path": [
						"api",
						"registration"
					]
				}
			},
			"response": []
		}
	]
}